spacy_spanish_lemmatizer/__init__.py
spacy_spanish_lemmatizer/__main__.py
spacy_spanish_lemmatizer/config.py
spacy_spanish_lemmatizer/lemmatizer.py
spacy_spanish_lemmatizer/main.py
spacy_spanish_lemmatizer/common/exceptions.json
spacy_spanish_lemmatizer/common/rules.json
spacy_spanish_lemmatizer/data/.gitignore
spacy_spanish_lemmatizer/parser/__init__.py
spacy_spanish_lemmatizer/parser/base_parser.py
spacy_spanish_lemmatizer/parser/parser_factory.py
spacy_spanish_lemmatizer/parser/wiki_parser.py
spacy_spanish_lemmatizer/tmp/.gitignore
spacy_spanish_lemmatizer-0.6.dist-info/LICENSE
spacy_spanish_lemmatizer-0.6.dist-info/METADATA
spacy_spanish_lemmatizer-0.6.dist-info/WHEEL
spacy_spanish_lemmatizer-0.6.dist-info/top_level.txt
spacy_spanish_lemmatizer-0.6.dist-info/RECORD
