Metadata-Version: 2.1
Name: spacy-spanish-lemmatizer
Version: 0.6
Summary: Spanish rule-based lemmatization for spaCy
Home-page: https://github.com/pablodms/spacy-spanish-lemmatizer
Author: Pablo David Muñoz Sánchez
Author-email: pablodavid.munoz@gmail.com
License: MIT
Download-URL: https://github.com/pablodms/spacy-spanish-lemmatizer/archive/v_0.4.tar.gz
Keywords: Lemmatization,spaCy,Spanish
Platform: UNKNOWN
Classifier: Development Status :: 2 - Pre-Alpha
Classifier: Intended Audience :: Developers
Classifier: Topic :: Software Development :: Build Tools
Classifier: License :: OSI Approved :: MIT License
Classifier: Programming Language :: Python :: 3.5
Classifier: Programming Language :: Python :: 3.6
Classifier: Programming Language :: Python :: 3.7
Requires-Dist: spacy (>=3.0)
